search_fusion_mcp-2.0.0.dist-info/licenses/LICENSE
src/__init__.py
src/main.py
src/search_manager.py
src/server.py
src/web_fetcher.py
src/config/__init__.py
src/config/config_manager.py
src/engines/__init__.py
src/engines/baidu_search.py
src/engines/base.py
src/engines/bing_search.py
src/engines/duckduckgo_search.py
src/engines/exa_search.py
src/engines/google_search.py
src/engines/jina_search.py
src/engines/serper_search.py
search_fusion_mcp-2.0.0.dist-info/METADATA
search_fusion_mcp-2.0.0.dist-info/WHEEL
search_fusion_mcp-2.0.0.dist-info/entry_points.txt
search_fusion_mcp-2.0.0.dist-info/top_level.txt
search_fusion_mcp-2.0.0.dist-info/RECORD
