Metadata-Version: 2.4
Name: search-fusion-mcp
Version: 2.0.0
Summary: 🔍 High-Availability Multi-Engine Search Aggregation MCP Server with Enhanced Proxy Auto-Detection
Home-page: https://github.com/sailaoda/search-fusion-mcp
Author: sailaoda
Author-email: Search Fusion Team <contact@searchfusion.dev>
Maintainer-email: Search Fusion Team <contact@searchfusion.dev>
License: MIT License
Project-URL: Homepage, https://github.com/sailaoda/search-fusion-mcp
Project-URL: Documentation, https://github.com/sailaoda/search-fusion-mcp/blob/main/README.md
Project-URL: Repository, https://github.com/sailaoda/search-fusion-mcp
Project-URL: Bug Tracker, https://github.com/sailaoda/search-fusion-mcp/issues
Project-URL: Changelog, https://github.com/sailaoda/search-fusion-mcp/blob/main/CHANGELOG.md
Keywords: mcp,search,aggregation,ai,llm,jina,google,serper,duckduckgo,bing,baidu,exa,wikipedia,web-scraping,high-availability,failover,multi-engine
Classifier: Development Status :: 5 - Production/Stable
Classifier: Intended Audience :: Developers
Classifier: License :: OSI Approved :: MIT License
Classifier: Operating System :: OS Independent
Classifier: Programming Language :: Python :: 3
Classifier: Programming Language :: Python :: 3.8
Classifier: Programming Language :: Python :: 3.9
Classifier: Programming Language :: Python :: 3.10
Classifier: Programming Language :: Python :: 3.11
Classifier: Programming Language :: Python :: 3.12
Classifier: Topic :: Internet :: WWW/HTTP :: Indexing/Search
Classifier: Topic :: Software Development :: Libraries :: Python Modules
Classifier: Topic :: Text Processing :: Indexing
Requires-Python: >=3.8
License-File: LICENSE
Requires-Dist: fastapi>=0.95.1
Requires-Dist: uvicorn>=0.22.0
Requires-Dist: httpx>=0.24.1
Requires-Dist: pydantic>=2.0.0
Requires-Dist: python-dotenv>=1.0.0
Requires-Dist: mcp>=0.1.0
Requires-Dist: duckduckgo_search>=3.9.5
Requires-Dist: backoff>=2.2.1
Requires-Dist: beautifulsoup4>=4.12.2
Requires-Dist: loguru>=0.7.0
Requires-Dist: rich>=13.7.0
Requires-Dist: exa-py>=0.6.0
Requires-Dist: wikipedia>=1.4.0
Provides-Extra: dev
Requires-Dist: pytest>=7.4.3; extra == "dev"
Requires-Dist: pytest-asyncio>=0.21.1; extra == "dev"
Requires-Dist: black>=23.0.0; extra == "dev"
Requires-Dist: flake8>=6.0.0; extra == "dev"
Requires-Dist: mypy>=1.0.0; extra == "dev"
Provides-Extra: all
Requires-Dist: pytest>=7.4.3; extra == "all"
Requires-Dist: pytest-asyncio>=0.21.1; extra == "all"
Requires-Dist: black>=23.0.0; extra == "all"
Requires-Dist: flake8>=6.0.0; extra == "all"
Requires-Dist: mypy>=1.0.0; extra == "all"
Dynamic: author
Dynamic: home-page
Dynamic: license-file
Dynamic: requires-python
